kombustion/__init__.py
kombustion-0.1.dist-info/DESCRIPTION.rst
kombustion-0.1.dist-info/METADATA
kombustion-0.1.dist-info/RECORD
kombustion-0.1.dist-info/WHEEL
kombustion-0.1.dist-info/metadata.json
kombustion-0.1.dist-info/top_level.txt
