Metadata-Version: 2.0
Name: kombustion
Version: 0.1
Summary: Eat a dict
Home-page: https://github.com/eL0ck/Kombustion
Author: eL0ck
Author-email: tpj800@gmail.com
License: MIT
Platform: UNKNOWN
